freqtools/__init__.py
freqtools/_version.py
freqtools/freq_data.py
freqtools/freq_models.py
freqtools/time_data.py
freqtools/transfer_functions.py
freqtools-0.1.0.dist-info/LICENSE
freqtools-0.1.0.dist-info/METADATA
freqtools-0.1.0.dist-info/WHEEL
freqtools-0.1.0.dist-info/top_level.txt
freqtools-0.1.0.dist-info/RECORD
