Metadata-Version: 2.1
Name: freqtools
Version: 0.1.0
Summary: Tools for phase and frequency data
Home-page: https://github.com/bleykauf/lab_data_logger
Author: Bastian Leykauf
Author-email: leykauf@physik.hu-berlin.de
Maintainer: Bastian Leykauf
Maintainer-email: leykauf@physik.hu-berlin.de
License: UNKNOWN
Platform: UNKNOWN
Classifier: Programming Language :: Python :: 3
Classifier: Intended Audience :: Science/Research
Requires-Python: >=3.5
License-File: LICENSE
Requires-Dist: numpy
Requires-Dist: allantools
Requires-Dist: scipy
Requires-Dist: matplotlib
